{"trial_id": "a6fe566a1c48e4a100e3d267ae0e82c4", "hyperparameters": {"space": [{"class_name": "Choice", "config": {"name": "structured_data_block_2/dense_block_1/num_layers", "default": 2, "conditions": [], "values": [1, 2, 3], "ordered": true}}, {"class_name": "Boolean", "config": {"name": "structured_data_block_2/dense_block_1/use_batchnorm", "default": false, "conditions": []}}, {"class_name": "Choice", "config": {"name": "structured_data_block_2/dense_block_1/dropout", "default": 0, "conditions": [], "values": [0.0, 0.25, 0.5], "ordered": true}}, {"class_name": "Choice", "config": {"name": "structured_data_block_2/dense_block_1/units_0", "default": 32, "conditions": [], "values": [16, 32, 64, 128, 256, 512, 1024], "ordered": true}}, {"class_name": "Choice", "config": {"name": "structured_data_block_2/dense_block_1/units_1", "default": 32, "conditions": [], "values": [16, 32, 64, 128, 256, 512, 1024], "ordered": true}}, {"class_name": "Choice", "config": {"name": "classification_head_2/dropout", "default": 0, "conditions": [], "values": [0.0, 0.25, 0.5], "ordered": true}}, {"class_name": "Choice", "config": {"name": "optimizer", "default": "adam", "conditions": [], "values": ["adam", "adadelta", "sgd"], "ordered": false}}, {"class_name": "Choice", "config": {"name": "learning_rate", "default": 0.001, "conditions": [], "values": [0.1, 0.01, 0.001, 0.0001, 1e-05], "ordered": true}}, {"class_name": "Choice", "config": {"name": "structured_data_block_2/dense_block_1/units_2", "default": 32, "conditions": [], "values": [16, 32, 64, 128, 256, 512, 1024], "ordered": true}}], "values": {"structured_data_block_2/dense_block_1/num_layers": 3, "structured_data_block_2/dense_block_1/use_batchnorm": true, "structured_data_block_2/dense_block_1/dropout": 0.25, "structured_data_block_2/dense_block_1/units_0": 32, "structured_data_block_2/dense_block_1/units_1": 512, "classification_head_2/dropout": 0, "optimizer": "adam", "learning_rate": 0.001, "structured_data_block_2/dense_block_1/units_2": 256}}, "metrics": {"metrics": {"loss": {"direction": "min", "observations": [{"value": [0.7463858127593994], "step": 0}, {"value": [0.7487596273422241], "step": 1}, {"value": [0.7251938581466675], "step": 2}, {"value": [0.7083081603050232], "step": 3}, {"value": [0.6801826357841492], "step": 4}, {"value": [0.697971761226654], "step": 5}, {"value": [0.6801366209983826], "step": 6}, {"value": [0.6668838858604431], "step": 7}, {"value": [0.6524779200553894], "step": 8}, {"value": [0.6743168234825134], "step": 9}, {"value": [0.6422366499900818], "step": 10}, {"value": [0.67633455991745], "step": 11}, {"value": [0.64893639087677], "step": 12}, {"value": [0.6460812091827393], "step": 13}, {"value": [0.6369326710700989], "step": 14}, {"value": [0.6674032807350159], "step": 15}, {"value": [0.6437303423881531], "step": 16}, {"value": [0.6462842226028442], "step": 17}, {"value": [0.6481915712356567], "step": 18}, {"value": [0.6634312868118286], "step": 19}, {"value": [0.6493791341781616], "step": 20}, {"value": [0.638796329498291], "step": 21}, {"value": [0.6366667747497559], "step": 22}, {"value": [0.648819088935852], "step": 23}, {"value": [0.6393908262252808], "step": 24}, {"value": [0.6467191576957703], "step": 25}, {"value": [0.6438438892364502], "step": 26}]}, "accuracy": {"direction": "max", "observations": [{"value": [0.57201087474823], "step": 0}, {"value": [0.59375], "step": 1}, {"value": [0.604619562625885], "step": 2}, {"value": [0.5896739363670349], "step": 3}, {"value": [0.616847813129425], "step": 4}, {"value": [0.6209239363670349], "step": 5}, {"value": [0.6304348111152649], "step": 6}, {"value": [0.61548912525177], "step": 7}, {"value": [0.6317934989929199], "step": 8}, {"value": [0.6086956262588501], "step": 9}, {"value": [0.648097813129425], "step": 10}, {"value": [0.6385869383811951], "step": 11}, {"value": [0.6413043737411499], "step": 12}, {"value": [0.6317934989929199], "step": 13}, {"value": [0.645380437374115], "step": 14}, {"value": [0.6290760636329651], "step": 15}, {"value": [0.6426630616188049], "step": 16}, {"value": [0.63451087474823], "step": 17}, {"value": [0.635869562625885], "step": 18}, {"value": [0.6317934989929199], "step": 19}, {"value": [0.635869562625885], "step": 20}, {"value": [0.648097813129425], "step": 21}, {"value": [0.64402174949646], "step": 22}, {"value": [0.6195651888847351], "step": 23}, {"value": [0.645380437374115], "step": 24}, {"value": [0.63451087474823], "step": 25}, {"value": [0.635869562625885], "step": 26}]}, "val_loss": {"direction": "min", "observations": [{"value": [0.6792930364608765], "step": 0}, {"value": [0.6374544501304626], "step": 1}, {"value": [0.6461355686187744], "step": 2}, {"value": [0.6222410798072815], "step": 3}, {"value": [0.6219033002853394], "step": 4}, {"value": [0.6057363748550415], "step": 5}, {"value": [0.6106797456741333], "step": 6}, {"value": [0.6112324595451355], "step": 7}, {"value": [0.6059470772743225], "step": 8}, {"value": [0.6029345393180847], "step": 9}, {"value": [0.5955718755722046], "step": 10}, {"value": [0.6068047285079956], "step": 11}, {"value": [0.6099097728729248], "step": 12}, {"value": [0.6006908416748047], "step": 13}, {"value": [0.6086392998695374], "step": 14}, {"value": [0.6032691597938538], "step": 15}, {"value": [0.5822135210037231], "step": 16}, {"value": [0.5969629883766174], "step": 17}, {"value": [0.5866770148277283], "step": 18}, {"value": [0.595792829990387], "step": 19}, {"value": [0.5845957398414612], "step": 20}, {"value": [0.5978155136108398], "step": 21}, {"value": [0.5909679532051086], "step": 22}, {"value": [0.5906717777252197], "step": 23}, {"value": [0.592736542224884], "step": 24}, {"value": [0.598223865032196], "step": 25}, {"value": [0.5970374345779419], "step": 26}]}, "val_accuracy": {"direction": "max", "observations": [{"value": [0.6451612710952759], "step": 0}, {"value": [0.7290322780609131], "step": 1}, {"value": [0.6709677577018738], "step": 2}, {"value": [0.6903225779533386], "step": 3}, {"value": [0.6838709712028503], "step": 4}, {"value": [0.6967741847038269], "step": 5}, {"value": [0.7096773982048035], "step": 6}, {"value": [0.7032257914543152], "step": 7}, {"value": [0.6903225779533386], "step": 8}, {"value": [0.6774193644523621], "step": 9}, {"value": [0.6903225779533386], "step": 10}, {"value": [0.6774193644523621], "step": 11}, {"value": [0.6645161509513855], "step": 12}, {"value": [0.6709677577018738], "step": 13}, {"value": [0.7161290049552917], "step": 14}, {"value": [0.6838709712028503], "step": 15}, {"value": [0.6838709712028503], "step": 16}, {"value": [0.7161290049552917], "step": 17}, {"value": [0.7290322780609131], "step": 18}, {"value": [0.7225806713104248], "step": 19}, {"value": [0.7225806713104248], "step": 20}, {"value": [0.6903225779533386], "step": 21}, {"value": [0.6967741847038269], "step": 22}, {"value": [0.7161290049552917], "step": 23}, {"value": [0.7161290049552917], "step": 24}, {"value": [0.7032257914543152], "step": 25}, {"value": [0.6903225779533386], "step": 26}]}}}, "score": 0.7290322780609131, "best_step": 1, "status": "COMPLETED"}